LICENSE
MANIFEST.in
README.rst
setup.cfg
setup.py
2.7/diffusion_ga.py
2.7/migration_ga.py
2.7/real_ga.py
2.7/standard_ga.py
2.7/benchmark/my_experiment.py
2.7/benchmark/my_timing.py
2.7/benchmark/pproc.py
benchmarking/README.md
benchmarking/diffusion_ga.zip
benchmarking/migration_ga.zip
benchmarking/ppdata.zip
benchmarking/standard_ga.zip
docs/Makefile
docs/conf.py
docs/geneticalgs.rst
docs/index.rst
docs/intro.rst
docs/make.bat
docs/modules.rst
docs/requirements.txt
examples/example.ipynb
examples/data/README.md
examples/data/inst.zip
examples/data/sol.zip
geneticalgs/__init__.py
geneticalgs/binary_ga.py
geneticalgs/diffusion_ga.py
geneticalgs/migration_ga.py
geneticalgs/real_ga.py
geneticalgs/standard_ga.py
geneticalgs.egg-info/PKG-INFO
geneticalgs.egg-info/SOURCES.txt
geneticalgs.egg-info/dependency_links.txt
geneticalgs.egg-info/requires.txt
geneticalgs.egg-info/top_level.txt
tests/helper_functions.py
tests/test_binary_ga.py
tests/test_diffusion_ga.py
tests/test_migration_ga.py
tests/test_real_ga.py
tests/test_standard_ga.py
time_complexity/all_algs_runs.png
time_complexity/box_and_whisker_run_plot.png
time_complexity/box_and_whisker_time_plot.png
time_complexity/mga_time.png
time_complexity/sga_dga_time.png
time_complexity/timing_dga.txt
time_complexity/timing_mga.txt
time_complexity/timing_sga.txt