Metadata-Version: 1.1
Name: geneticalgs
Version: 1.0
Summary: Implementation of standard, diffusion and migration models of genetic algorithms.
Home-page: https://github.com/bobirdmi
Author: Dmitriy Bobir
Author-email: bobirdima@gmail.com
License: Public Domain
Keywords: evolutionary algorithms,genetic algorithms,optimalization,best combination,function minimum,function maximum
Platform: UNKNOWN
Classifier: Intended Audience :: Developers
Classifier: Intended Audience :: Science/Research
Classifier: License :: OSI Approved :: Apache Software License
Classifier: License :: Public Domain
Classifier: Operating System :: Microsoft :: Windows
Classifier: Operating System :: POSIX :: Linux
Classifier: Programming Language :: Python
Classifier: Programming Language :: Python :: 3
Classifier: Programming Language :: Python :: 3.5
Classifier: Topic :: Scientific/Engineering
Classifier: Topic :: Software Development :: Libraries
Classifier: Topic :: Software Development :: Libraries :: Python Modules
